mkdocs_plugin_wikipedia/__init__.py
mkdocs_plugin_wikipedia/css/wiki.css
mkdocs_plugin_wikipedia/js/wiki-tips.js
mkdocs_plugin_wikipedia/plugin.py
mkdocs_plugin_wikipedia/wikipedia.py
mkdocs_wikipedia-0.1.0.dist-info/METADATA
mkdocs_wikipedia-0.1.0.dist-info/WHEEL
mkdocs_wikipedia-0.1.0.dist-info/entry_points.txt
mkdocs_wikipedia-0.1.0.dist-info/licenses/LICENSE.md
mkdocs_wikipedia-0.1.0.dist-info/RECORD
