Metadata-Version: 2.4
Name: mkdocs-wikipedia
Version: 0.1.0
Summary: Add overlay on wikipedia links in MkDocs
License: MIT
License-File: LICENSE.md
Keywords: mkdocs,python,wiki,wikipedia
Author: Yves Chevallier
Author-email: yves.chevallier@heig-vd.ch
Requires-Python: >=3.9,<4.0
Classifier: Development Status :: 4 - Beta
Classifier: Intended Audience :: Developers
Classifier: Intended Audience :: Information Technology
Classifier: License :: OSI Approved :: MIT License
Classifier: Programming Language :: Python
Classifier: Programming Language :: Python :: 3
Classifier: Programming Language :: Python :: 3.9
Classifier: Programming Language :: Python :: 3.10
Classifier: Programming Language :: Python :: 3.11
Classifier: Programming Language :: Python :: 3.12
Classifier: Programming Language :: Python :: 3.13
Classifier: Programming Language :: Python :: 3.14
Classifier: Programming Language :: Python :: 3 :: Only
Requires-Dist: mkdocs (>=1.6.1,<2.0.0)
Requires-Dist: pydantic (>=2.9.2,<3.0.0)
Requires-Dist: ruamel-yaml (>=0.18.15,<0.19.0)
Requires-Dist: unidecode (>=1.4.0,<2.0.0)
Project-URL: Documentation, https://github.com/yves-chevallier/mkdocs-wikipedia
Project-URL: Source, https://github.com/yves-chevallier/mkdocs-wikipedia
Project-URL: Tracker, https://github.com/yves-chevallier/mkdocs-wikipedia/issues
